morpht5/__init__.py
morpht5/constants.py
morpht5/models/__init__.py
morpht5/models/modeling_morph_t5_auto.py
morpht5/models/modeling_morph_t5_concat.py
morpht5/models/modeling_morph_t5_sum.py
morpht5/tagsets/__init__.py
morpht5/tagsets/biblehub.py
morpht5/tagsets/oblubienica.py
morpht5/tokenizer/__init__.py
morpht5/tokenizer/morph_t5_tokenizer.py
morpht5/tokenizer/morph_tokenizer.py
morpht5/tokenizer/utils.py
morpht5/utils/formatting.py
morpht5-0.2.2.dist-info/METADATA
morpht5-0.2.2.dist-info/WHEEL
morpht5-0.2.2.dist-info/RECORD
