Metadata-Version: 2.1
Name: morpht5
Version: 0.2.2
Summary: A morphologically aware version of T5 model.
License: MIT
Author: Maciej Rapacz
Author-email: mrapacz@agh.edu.pl
Requires-Python: >=3.11,<4.0
Classifier: License :: OSI Approved :: MIT License
Classifier: Programming Language :: Python :: 3
Classifier: Programming Language :: Python :: 3.11
Classifier: Programming Language :: Python :: 3.12
Classifier: Programming Language :: Python :: 3.13
Requires-Dist: torch (>=2,<3)
Requires-Dist: transformers (>=4,<5)
